qt6_tools/__init__.py
qt6_tools/_version.py
qt6_tools/entrypoints.py
qt6_tools/tests/__init__.py
qt6_tools/tests/test_entrypoints.py
qt6_tools-6.3.2.1.3.dist-info/COPYING
qt6_tools-6.3.2.1.3.dist-info/METADATA
qt6_tools-6.3.2.1.3.dist-info/WHEEL
qt6_tools-6.3.2.1.3.dist-info/entry_points.txt
qt6_tools-6.3.2.1.3.dist-info/top_level.txt
qt6_tools-6.3.2.1.3.dist-info/RECORD
