Metadata-Version: 2.1
Name: qt6-tools
Version: 6.3.2.1.3
Summary: Wrappers for the raw Qt programs from qt6-applications
Home-page: https://github.com/altendky/qt-tools
Author: Kyle Altendorf
Author-email: sda@fstab.net
License: LGPLv3
Classifier: Development Status :: 4 - Beta
Classifier: Intended Audience :: Developers
Classifier: License :: OSI Approved :: GNU Lesser General Public License v3 (LGPLv3)
Classifier: Operating System :: POSIX :: Linux
Classifier: Operating System :: MacOS :: MacOS X
Classifier: Operating System :: Microsoft :: Windows
Classifier: Programming Language :: Python :: 3
Classifier: Programming Language :: Python :: 3.5
Classifier: Programming Language :: Python :: 3.6
Classifier: Programming Language :: Python :: 3.7
Classifier: Programming Language :: Python :: 3.8
Classifier: Programming Language :: Python :: 3.9
Classifier: Topic :: Software Development
Classifier: Topic :: Utilities
Requires-Python: >=3.7
License-File: COPYING
Requires-Dist: qt6-applications (<6.3.2.3,>=6.3.2.2.2)
Requires-Dist: click
